nbb_api/__init__.py
nbb_api/ldb.py
nbb_api/liga_ouro.py
nbb_api/nbb.py
nbb_api-0.1.11.dist-info/METADATA
nbb_api-0.1.11.dist-info/WHEEL
nbb_api-0.1.11.dist-info/top_level.txt
nbb_api-0.1.11.dist-info/RECORD
