Metadata-Version: 2.1
Name: nbb_api
Version: 0.1.11
Summary: Python package for easy access to Brazilian basketball data: NBB (Novo Basquete Brasil), Liga Ouro and LDB
Home-page: https://github.com/GabrielPastorello/nbb_api
Author: Gabriel Speranza Pastorello
Author-email: gabriel.pastorello01@gmail.com
License: MIT
Keywords: nbb,novo basquete brasil,scraper,basketball,international basketball,brazil,ldb,liga-ouro
Classifier: Programming Language :: Python :: 3
Classifier: License :: OSI Approved :: MIT License
Classifier: Operating System :: OS Independent
Requires-Python: >=3.6
Requires-Dist: pandas >=1.5.3
Requires-Dist: numpy >=1.24.1
Requires-Dist: python-dateutil >=2.8.2
Requires-Dist: pytz >=2022.7
Requires-Dist: lxml >=4.9.2
